gtfsscheduleviewer/__init__.py
gtfsscheduleviewer/marey_graph.py
gtfsscheduleviewer/files/calendarpopup.js
gtfsscheduleviewer/files/index.html
gtfsscheduleviewer/files/index.js
gtfsscheduleviewer/files/labeled_marker.js
gtfsscheduleviewer/files/markerwithlabel.js
gtfsscheduleviewer/files/mm_20_blue.png
gtfsscheduleviewer/files/mm_20_blue_trans.png
gtfsscheduleviewer/files/mm_20_red_trans.png
gtfsscheduleviewer/files/mm_20_shadow.png
gtfsscheduleviewer/files/mm_20_shadow_trans.png
gtfsscheduleviewer/files/mm_20_yellow.png
gtfsscheduleviewer/files/style.css
gtfsscheduleviewer/files/svgcheck.vbs
transitfeed/__init__.py
transitfeed/agency.py
transitfeed/compat.py
transitfeed/errors.py
transitfeed/fareattribute.py
transitfeed/farerule.py
transitfeed/feedinfo.py
transitfeed/frequency.py
transitfeed/gtfsfactory.py
transitfeed/gtfsfactoryuser.py
transitfeed/gtfsobjectbase.py
transitfeed/loader.py
transitfeed/problems.py
transitfeed/route.py
transitfeed/schedule.py
transitfeed/serviceperiod.py
transitfeed/shape.py
transitfeed/shapelib.py
transitfeed/shapeloader.py
transitfeed/shapepoint.py
transitfeed/stop.py
transitfeed/stoptime.py
transitfeed/transfer.py
transitfeed/trip.py
transitfeed/util.py
transitfeed/version.py
transitfeed_py3-1.2.16.data/scripts/feedvalidator.py
transitfeed_py3-1.2.16.data/scripts/feedvalidator_googletransit.py
transitfeed_py3-1.2.16.data/scripts/kmlparser.py
transitfeed_py3-1.2.16.data/scripts/kmlwriter.py
transitfeed_py3-1.2.16.data/scripts/location_editor.py
transitfeed_py3-1.2.16.data/scripts/merge.py
transitfeed_py3-1.2.16.data/scripts/schedule_viewer.py
transitfeed_py3-1.2.16.data/scripts/shape_importer.py
transitfeed_py3-1.2.16.data/scripts/unusual_trip_filter.py
transitfeed_py3-1.2.16.data/scripts/upgrade_translations.py
transitfeed_py3-1.2.16.data/scripts/visualize_pathways.py
transitfeed_py3-1.2.16.dist-info/COPYING
transitfeed_py3-1.2.16.dist-info/METADATA
transitfeed_py3-1.2.16.dist-info/WHEEL
transitfeed_py3-1.2.16.dist-info/top_level.txt
transitfeed_py3-1.2.16.dist-info/RECORD
